Metadata-Version: 2.1
Name: tracker-cli
Version: 2.2
Summary: Client for connecting the tracker to the TrackerContest application
Author-email: genimotion@ya.ru
